Metadata-Version: 2.1
Name: openport
Version: 0.0.3
Summary: A very basic function
Home-page: UNKNOWN
Author: Ao Zhang
Author-email: aozhang2022@gmail.com
License: MIT
Keywords: calculator
Platform: UNKNOWN
Classifier: Development Status :: 5 - Production/Stable
Classifier: Intended Audience :: Education
Classifier: Operating System :: Microsoft :: Windows :: Windows 10
Classifier: License :: OSI Approved :: MIT License
Classifier: Programming Language :: Python :: 3
License-File: LICENCE
